text_processing_ml/__init__.py
text_processing_ml/matching/__init__.py
text_processing_ml/matching/matching.py
text_processing_ml/normalization/__init__.py
text_processing_ml/normalization/normalization.py
text_processing_ml/parsing/__init__.py
text_processing_ml/parsing/parsing.py
text_processing_ml-0.2.0.dist-info/METADATA
text_processing_ml-0.2.0.dist-info/WHEEL
text_processing_ml-0.2.0.dist-info/top_level.txt
text_processing_ml-0.2.0.dist-info/RECORD
